sqlalchemy_dialects/es/__init__.py
sqlalchemy_dialects/es/api.py
sqlalchemy_dialects/es/baseapi.py
sqlalchemy_dialects/es/basesqlalchemy.py
sqlalchemy_dialects/es/const.py
sqlalchemy_dialects/es/exceptions.py
sqlalchemy_dialects/es/sqlalchemy.py
sqlalchemy_dialects/es/aws/__init__.py
sqlalchemy_dialects/es/aws/api.py
sqlalchemy_dialects/es/aws/sqlalchemy.py
tests/_0_fixtures_test.py
tests/__init__.py
tests/dbapi_test.py
tests/sqlalchemy_test.py
tests/fixtures/__init__.py
tests/fixtures/fixtures.py
tests/scripts/export.py
sqlalchemy_es-0.1.0a0.dist-info/LICENSE.txt
sqlalchemy_es-0.1.0a0.dist-info/METADATA
sqlalchemy_es-0.1.0a0.dist-info/WHEEL
sqlalchemy_es-0.1.0a0.dist-info/entry_points.txt
sqlalchemy_es-0.1.0a0.dist-info/top_level.txt
sqlalchemy_es-0.1.0a0.dist-info/RECORD
