Metadata-Version: 2.1
Name: sqlalchemy-es
Version: 0.1.0a0
Summary: SQLAlchemy dialect for Elasticsearch with write operations support
Home-page: https://github.com/usalko
Download-URL: https://github.com/usalko/elasticsearch-es/releases/tag/0.1.0a
Author: 
Author-email: 
License: Apache License, Version 2.0
Platform: UNKNOWN
Classifier: Programming Language :: Python :: 3.6
Classifier: Programming Language :: Python :: 3.7
Classifier: Programming Language :: Python :: 3.8
Classifier: Programming Language :: Python :: 3.9
Classifier: Programming Language :: Python :: 3.10
License-File: LICENSE.txt
Requires-Dist: elasticsearch (<7.14,>7)
Requires-Dist: packaging (<22.0,>=21.0)
Requires-Dist: sqlalchemy
Provides-Extra: opendistro
Requires-Dist: requests-aws4auth ; extra == 'opendistro'
Requires-Dist: boto3 ; extra == 'opendistro'
